thedoc/__init__.py
thedoc/cli.py
thedoc/config.py
thedoc/mkdocs_generator.py
thedoc/parsers/__init__.py
thedoc/parsers/base.py
thedoc/parsers/dotnet_parser.py
thedoc/parsers/kotlin_parser.py
thedoc/parsers/python.py
thedoc/parsers/swift_parser.py
thedoc-0.1.1.dist-info/METADATA
thedoc-0.1.1.dist-info/WHEEL
thedoc-0.1.1.dist-info/entry_points.txt
thedoc-0.1.1.dist-info/RECORD
